[{"full_picture":"https://scontent-iad3-2.xx.fbcdn.net/v/t39.30808-6/441145129_1509158363132665_4666846973354237659_n.jpg?stp=dst-jpg_p720x720&_nc_cat=106&ccb=1-7&_nc_sid=5f2048&_nc_ohc=OzqDPC5KTOsQ7kNvgHHEfxR&_nc_ht=scontent-iad3-2.xx&edm=AKK4YLsEAAAA&oh=00_AYBUA1mHCvlcgJbXg0J88wgpyiXij9Ib5Zf_f5pnMOtyWQ&oe=6649D647","attachments":{"data":[{"description":"Valo kaareutuu ja on täynnä kultaa! Suomen ainoa ja ylivoimaisesti paras lesbokuoro Kaupungin Naiset laulaa runoutta auringonjumala Balderin silmien alla.\n\nTule nauttimaan laulusta, sanataiteesta ja uljaista naisista Balderin saliin Helsinki Pride -viikon perjantaina 28.6.2024.\n\nKaupungin Naiset esittää sille sävellettyä suomalaista nykyrunoutta ja juhlii tänä vuonna kymmenvuotista laulutaivaltaan.\n\nLiput \"Kaupungin Naiset 10: Oli hiki vaikka oli ilta\" -konserttiin voit ostaa ennakkoon Menokoneen lippupalvelusta: https://www.hs.fi/menokone/events/119246/681884/tickets\n\nLämpimästi tervetuloa kaikki!\n\nEsteettömyystiedot Balderin sali verkkosivuilta: https://www.balder.fi/","media":{"image":{"height":720,"src":"https://scontent-iad3-2.xx.fbcdn.net/v/t39.30808-6/441145129_1509158363132665_4666846973354237659_n.jpg?stp=dst-jpg_p720x720&_nc_cat=106&ccb=1-7&_nc_sid=5f2048&_nc_ohc=OzqDPC5KTOsQ7kNvgHHEfxR&_nc_ht=scontent-iad3-2.xx&edm=AKK4YLsEAAAA&oh=00_AYBUA1mHCvlcgJbXg0J88wgpyiXij9Ib5Zf_f5pnMOtyWQ&oe=6649D647","width":1278}},"target":{"id":"1509158379799330","url":"https://www.facebook.com/photo.php?fbid=1509158379799330&set=a.1092104914838014&type=3"},"type":"photo","url":"https://www.facebook.com/photo.php?fbid=1509158379799330&set=a.1092104914838014&type=3"}]},"message":"Valo kaareutuu ja on täynnä kultaa! Suomen ainoa ja ylivoimaisesti paras lesbokuoro Kaupungin Naiset laulaa runoutta auringonjumala Balderin silmien alla.\n\nTule nauttimaan laulusta, sanataiteesta ja uljaista naisista Balderin saliin Helsinki Pride -viikon perjantaina 28.6.2024.\n\nKaupungin Naiset esittää sille sävellettyä suomalaista nykyrunoutta ja juhlii tänä vuonna kymmenvuotista laulutaivaltaan.\n\nLiput \"Kaupungin Naiset 10: Oli hiki vaikka oli ilta\" -konserttiin voit ostaa ennakkoon Menokoneen lippupalvelusta: https://www.hs.fi/menokone/events/119246/681884/tickets\n\nLämpimästi tervetuloa kaikki!\n\nEsteettömyystiedot Balderin sali verkkosivuilta: https://www.balder.fi/","created_time":"2024-05-14T13:41:39+0000","id":"733633953363297_1509159226465912"},{"full_picture":"https://scontent-iad3-1.xx.fbcdn.net/v/t39.30808-6/424657358_1509147263133775_8392313075916263421_n.jpg?stp=c279.0.720.720a_dst-jpg_p720x720&_nc_cat=107&ccb=1-7&_nc_sid=5f2048&_nc_ohc=1SWuw6_firMQ7kNvgGQGTv1&_nc_oc=AdiidWGBE3a-xZZQAHe0mvi2bDTNUZzp_s8qZKJv97VmE9-hthPxNYrh5t20bJiCwB0&_nc_ht=scontent-iad3-1.xx&edm=AKK4YLsEAAAA&oh=00_AYDTahcDhPlN01e-pjByrAEgn-6HS8nffH84WLHvkqBvoQ&oe=6649DFB5","attachments":{"data":[{"description":"14 osallistuu · 46 on kiinnostunut","media":{"image":{"height":720,"src":"https://scontent-iad3-1.xx.fbcdn.net/v/t39.30808-6/424657358_1509147263133775_8392313075916263421_n.jpg?stp=c279.0.720.720a_dst-jpg_p720x720&_nc_cat=107&ccb=1-7&_nc_sid=5f2048&_nc_ohc=1SWuw6_firMQ7kNvgGQGTv1&_nc_oc=AdiidWGBE3a-xZZQAHe0mvi2bDTNUZzp_s8qZKJv97VmE9-hthPxNYrh5t20bJiCwB0&_nc_ht=scontent-iad3-1.xx&edm=AKK4YLsEAAAA&oh=00_AYDTahcDhPlN01e-pjByrAEgn-6HS8nffH84WLHvkqBvoQ&oe=6649DFB5","width":720}},"target":{"id":"1008111740701500","url":"https://www.facebook.com/events/1008111740701500/"},"title":"Kaupungin Naiset 10: Oli hiki vaikka oli ilta","type":"event","url":"https://www.facebook.com/events/1008111740701500/"}]},"created_time":"2024-05-14T13:17:44+0000","id":"733633953363297_1008111740701500"},{"full_picture":"https://scontent-iad3-2.xx.fbcdn.net/v/t39.30808-6/440572158_1502253080489860_252167326370706572_n.jpg?_nc_cat=111&ccb=1-7&_nc_sid=5f2048&_nc_ohc=saBYvU2iTiYQ7kNvgGBmg3D&_nc_oc=AdjQvkNrbk4mYdI_-6pMvn1UCfuAr-oBuapgnDU3Kgfns9bAaX0MBOUqOF9Fmyg2S9U&_nc_ht=scontent-iad3-2.xx&edm=AKK4YLsEAAAA&oh=00_AYCcqMGQyGQWurIFtmJPrNfMv07YedSWWzX44LSR4Pgf4w&oe=6649E8D5","attachments":{"data":[{"description":"Liput tulossa myyntiin pian! 🤩","media":{"image":{"height":658,"src":"https://scontent-iad3-2.xx.fbcdn.net/v/t39.30808-6/440572158_1502253080489860_252167326370706572_n.jpg?_nc_cat=111&ccb=1-7&_nc_sid=5f2048&_nc_ohc=saBYvU2iTiYQ7kNvgGBmg3D&_nc_oc=AdjQvkNrbk4mYdI_-6pMvn1UCfuAr-oBuapgnDU3Kgfns9bAaX0MBOUqOF9Fmyg2S9U&_nc_ht=scontent-iad3-2.xx&edm=AKK4YLsEAAAA&oh=00_AYCcqMGQyGQWurIFtmJPrNfMv07YedSWWzX44LSR4Pgf4w&oe=6649E8D5","width":467}},"target":{"id":"1502253087156526","url":"https://www.facebook.com/photo.php?fbid=1502253087156526&set=a.1092104911504681&type=3"},"type":"photo","url":"https://www.facebook.com/photo.php?fbid=1502253087156526&set=a.1092104911504681&type=3"}]},"message":"Liput tulossa myyntiin pian! 🤩","created_time":"2024-05-04T14:38:33+0000","id":"733633953363297_1502253277156507"},{"full_picture":"https://scontent-iad3-2.xx.fbcdn.net/v/t39.30808-6/441156615_1501586057223229_5676922743602100408_n.jpg?stp=dst-jpg_p720x720&_nc_cat=100&ccb=1-7&_nc_sid=5f2048&_nc_ohc=ufgGxr9S2OcQ7kNvgEr7FSO&_nc_ht=scontent-iad3-2.xx&edm=AKK4YLsEAAAA&oh=00_AYAcLaS-bi2i0ghLVxDTK9Fsjl8VvOwpSWj1fQd_N6_01A&oe=6649E4D6","attachments":{"data":[{"media":{"image":{"height":959,"src":"https://scontent-iad3-2.xx.fbcdn.net/v/t39.30808-6/441156615_1501586057223229_5676922743602100408_n.jpg?stp=dst-jpg_p720x720&_nc_cat=100&ccb=1-7&_nc_sid=5f2048&_nc_ohc=ufgGxr9S2OcQ7kNvgEr7FSO&_nc_ht=scontent-iad3-2.xx&edm=AKK4YLsEAAAA&oh=00_AYAcLaS-bi2i0ghLVxDTK9Fsjl8VvOwpSWj1fQd_N6_01A&oe=6649E4D6","width":720}},"subattachments":{"data":[{"media":{"image":{"height":959,"src":"https://scontent-iad3-2.xx.fbcdn.net/v/t39.30808-6/441156615_1501586057223229_5676922743602100408_n.jpg?stp=dst-jpg_p720x720&_nc_cat=100&ccb=1-7&_nc_sid=5f2048&_nc_ohc=ufgGxr9S2OcQ7kNvgEr7FSO&_nc_ht=scontent-iad3-2.xx&edm=AKK4YLsEAAAA&oh=00_AYAcLaS-bi2i0ghLVxDTK9Fsjl8VvOwpSWj1fQd_N6_01A&oe=6649E4D6","width":720}},"target":{"id":"1501586060556562","url":"https://www.facebook.com/photo.php?fbid=1501586060556562&set=a.1092104911504681&type=3"},"type":"photo","url":"https://www.facebook.com/photo.php?fbid=1501586060556562&set=a.1092104911504681&type=3"},{"media":{"image":{"height":1600,"src":"https://scontent-iad3-1.xx.fbcdn.net/v/t39.30808-6/421964980_1501586117223223_7025432682348113843_n.jpg?stp=dst-jpg_p720x720&_nc_cat=110&ccb=1-7&_nc_sid=5f2048&_nc_ohc=duhZScWcyqYQ7kNvgEJJAnw&_nc_ht=scontent-iad3-1.xx&edm=AKK4YLsEAAAA&oh=00_AYD63zduYVm_Vdc1urFYqP-x3b8WT51MDaKIHRjnix3gVw&oe=6649E7E9","width":720}},"target":{"id":"1501586127223222","url":"https://www.facebook.com/photo.php?fbid=1501586127223222&set=a.1092104911504681&type=3"},"type":"photo","url":"https://www.facebook.com/photo.php?fbid=1501586127223222&set=a.1092104911504681&type=3"}]},"target":{"id":"1501586273889874","url":"https://www.facebook.com/1093346494713856/posts/1501586273889874"},"title":"Kuvat henkilön Kaupungin Naiset julkaisusta","type":"album","url":"https://www.facebook.com/1093346494713856/posts/1501586273889874"}]},"message":"Tänään Anja Erämajan \"Joku menee aina ensin\" kirjajulkkareissa!","created_time":"2024-05-03T15:26:42+0000","id":"733633953363297_1501586273889874"}]