[{"full_picture":"https://scontent-iad3-2.xx.fbcdn.net/v/t39.30808-6/284282108_5338357379557575_9033050375897648998_n.jpg?stp=dst-jpg_s720x720&_nc_cat=108&ccb=1-7&_nc_sid=8024bb&_nc_ohc=n9O57L2jWr8AX_rlVCX&_nc_ht=scontent-iad3-2.xx&edm=AKK4YLsEAAAA&oh=00_AT8cuobiLeHD703mSWN6M8ixRaK28mPi8B_tNRAMID5d-g&oe=629DED73","attachments":{"data":[{"description":"WOW!!! Puolet lipuista Helsinki Pride -viikon konserttiin meni yhdessä hujauksessa - kiitos ihanat että olette tulossa 😍\n\nKäy ostamassa omat lippusi täältä: https://bit.ly/3t5f1VQ\n\nKaupungin Naiset -kuoro on Suomen ainoa lesbokuoro ja jo vuodesta 2014 se on jankannut elämisen ja rakastamisen kauneudesta ja kurjuudesta.\n\n#helsinkipride #KaupunginNaiset #minäolenerehtymätön","media":{"image":{"height":405,"src":"https://scontent-iad3-2.xx.fbcdn.net/v/t39.30808-6/284282108_5338357379557575_9033050375897648998_n.jpg?stp=dst-jpg_s720x720&_nc_cat=108&ccb=1-7&_nc_sid=8024bb&_nc_ohc=n9O57L2jWr8AX_rlVCX&_nc_ht=scontent-iad3-2.xx&edm=AKK4YLsEAAAA&oh=00_AT8cuobiLeHD703mSWN6M8ixRaK28mPi8B_tNRAMID5d-g&oe=629DED73","width":720}},"target":{"id":"5338357389557574","url":"https://www.facebook.com/kaupunginnaiset/photos/a.733643153362377/5338357389557574/?type=3"},"type":"photo","url":"https://www.facebook.com/kaupunginnaiset/photos/a.733643153362377/5338357389557574/?type=3"}]},"message":"WOW!!! Puolet lipuista Helsinki Pride -viikon konserttiin meni yhdessä hujauksessa - kiitos ihanat että olette tulossa 😍\n\nKäy ostamassa omat lippusi täältä: https://bit.ly/3t5f1VQ\n\nKaupungin Naiset -kuoro on Suomen ainoa lesbokuoro ja jo vuodesta 2014 se on jankannut elämisen ja rakastamisen kauneudesta ja kurjuudesta.\n\n#helsinkipride #KaupunginNaiset #minäolenerehtymätön","created_time":"2022-06-01T04:52:02+0000","id":"733633953363297_5338364036223576"}]